postman_collection_generation/__init__.py
postman_collection_generation-1.0.0.dist-info/LICENSE
postman_collection_generation-1.0.0.dist-info/METADATA
postman_collection_generation-1.0.0.dist-info/WHEEL
postman_collection_generation-1.0.0.dist-info/entry_points.txt
postman_collection_generation-1.0.0.dist-info/top_level.txt
postman_collection_generation-1.0.0.dist-info/RECORD
