Metadata-Version: 2.1
Name: postman-collection-generation
Version: 1.0.0
Summary: postman collection generation
Home-page: https://github.com/AliaHamwi/PostmanCollection
Author: AliaHamwi
Author-email: Alia.Hamwi.95@gmail.com
License: MIT
Platform: UNKNOWN
Classifier: License :: OSI Approved :: MIT License
Classifier: Programming Language :: Python :: 3
Classifier: Programming Language :: Python :: 3.7
Requires-Dist: flask
